{
  "entities": [
    {
      "text": "Amit Bansal Alias Amit Agarwal",
      "label": "PETITIONER",
      "start_char": 17,
      "end_char": 47
    },
    {
      "text": "Csh Power Himoinsa Private Limited",
      "label": "RESPONDENT",
      "start_char": 51,
      "end_char": 85
    },
    {
      "text": "C.Hari Shankar",
      "label": "JUDGE",
      "start_char": 116,
      "end_char": 130
    },
    {
      "text": "C.Hari Shankar",
      "label": "JUDGE",
      "start_char": 138,
      "end_char": 152
    },
    {
      "text": "High Court Of Delhi At New Delhi",
      "label": "COURT",
      "start_char": 222,
      "end_char": 254
    },
    {
      "text": "Amit Bansal Alias Amit Agarwal",
      "label": "PETITIONER",
      "start_char": 424,
      "end_char": 454
    },
    {
      "text": "Mohit Kumar",
      "label": "LAWYER",
      "start_char": 534,
      "end_char": 545
    },
    {
      "text": "Ravinder Aggarwal",
      "label": "LAWYER",
      "start_char": 603,
      "end_char": 620
    },
    {
      "text": "Power Himoinsa Private Limited",
      "label": "RESPONDENT",
      "start_char": 733,
      "end_char": 763
    },
    {
      "text": "Rahul Malhotra",
      "label": "LAWYER",
      "start_char": 840,
      "end_char": 854
    },
    {
      "text": "Anchal Tiwari",
      "label": "LAWYER",
      "start_char": 912,
      "end_char": 925
    },
    {
      "text": "C.Hari Shankar",
      "label": "JUDGE",
      "start_char": 1032,
      "end_char": 1046
    },
    {
      "text": "Sugandhi v. P. Raj Kumar1",
      "label": "PRECEDENT",
      "start_char": 1279,
      "end_char": 1304
    },
    {
      "text": "Code of Civil Procedure, 1908",
      "label": "STATUTE",
      "start_char": 1378,
      "end_char": 1407
    },
    {
      "text": "(2020) 1 SCC 706",
      "label": "PRECEDENT",
      "start_char": 1936,
      "end_char": 1952
    },
    {
      "text": "subrule (3)",
      "label": "PROVISION",
      "start_char": 2194,
      "end_char": 2205
    },
    {
      "text": "CPC",
      "label": "STATUTE",
      "start_char": 2305,
      "end_char": 2308
    },
    {
      "text": "Article 227",
      "label": "PROVISION",
      "start_char": 2313,
      "end_char": 2324
    },
    {
      "text": "Constitution of India",
      "label": "STATUTE",
      "start_char": 2332,
      "end_char": 2353
    },
    {
      "text": "Raj Power Projects",
      "label": "ORG",
      "start_char": 2796,
      "end_char": 2814
    },
    {
      "text": "Tarun Sehgal",
      "label": "OTHER_PERSON",
      "start_char": 2846,
      "end_char": 2858
    },
    {
      "text": "Tarun Sehgal",
      "label": "OTHER_PERSON",
      "start_char": 2956,
      "end_char": 2968
    },
    {
      "text": "Amit Aggarwal",
      "label": "OTHER_PERSON",
      "start_char": 2976,
      "end_char": 2989
    },
    {
      "text": "Raj Power Projects",
      "label": "ORG",
      "start_char": 3021,
      "end_char": 3039
    },
    {
      "text": "Amit Bansal @ Amit Aggarwal",
      "label": "RESPONDENT",
      "start_char": 3170,
      "end_char": 3197
    },
    {
      "text": "Raj Power Project",
      "label": "ORG",
      "start_char": 3218,
      "end_char": 3235
    },
    {
      "text": "9 th March 2021",
      "label": "DATE",
      "start_char": 3253,
      "end_char": 3268
    },
    {
      "text": "Order VI Rule 17",
      "label": "PROVISION",
      "start_char": 3394,
      "end_char": 3410
    },
    {
      "text": "CPC",
      "label": "STATUTE",
      "start_char": 3418,
      "end_char": 3421
    },
    {
      "text": "Amit Bansal @ Amit Aggarwal",
      "label": "RESPONDENT",
      "start_char": 3534,
      "end_char": 3561
    },
    {
      "text": "Raj Power Project",
      "label": "ORG",
      "start_char": 3582,
      "end_char": 3599
    },
    {
      "text": "Raj Power Projects",
      "label": "ORG",
      "start_char": 3620,
      "end_char": 3638
    },
    {
      "text": "Tarun Sehgal",
      "label": "OTHER_PERSON",
      "start_char": 3670,
      "end_char": 3682
    },
    {
      "text": "29th July 2022",
      "label": "DATE",
      "start_char": 3924,
      "end_char": 3938
    },
    {
      "text": "Amit Bansal",
      "label": "PETITIONER",
      "start_char": 4001,
      "end_char": 4012
    },
    {
      "text": "Article 227",
      "label": "PROVISION",
      "start_char": 4064,
      "end_char": 4075
    },
    {
      "text": "Constitution of India",
      "label": "STATUTE",
      "start_char": 4083,
      "end_char": 4104
    },
    {
      "text": "Mohit Kumar",
      "label": "LAWYER",
      "start_char": 4139,
      "end_char": 4150
    },
    {
      "text": "Mohit Kumar",
      "label": "LAWYER",
      "start_char": 4197,
      "end_char": 4208
    },
    {
      "text": "Amit Bansal",
      "label": "PETITIONER",
      "start_char": 4384,
      "end_char": 4395
    },
    {
      "text": "Tarun Sehgal",
      "label": "OTHER_PERSON",
      "start_char": 4408,
      "end_char": 4420
    },
    {
      "text": "Amit Bansal",
      "label": "PETITIONER",
      "start_char": 4640,
      "end_char": 4651
    },
    {
      "text": "Amit Bansal",
      "label": "PETITIONER",
      "start_char": 4679,
      "end_char": 4690
    },
    {
      "text": "RPP",
      "label": "ORG",
      "start_char": 4720,
      "end_char": 4723
    },
    {
      "text": "Mohit Kumar",
      "label": "LAWYER",
      "start_char": 4860,
      "end_char": 4871
    },
    {
      "text": "Tarun Sehgal",
      "label": "OTHER_PERSON",
      "start_char": 4932,
      "end_char": 4944
    },
    {
      "text": "Amit Bansal",
      "label": "PETITIONER",
      "start_char": 5058,
      "end_char": 5069
    },
    {
      "text": "Tarun Sehgal",
      "label": "OTHER_PERSON",
      "start_char": 5103,
      "end_char": 5115
    },
    {
      "text": "CPC",
      "label": "STATUTE",
      "start_char": 5190,
      "end_char": 5193
    },
    {
      "text": "Mohit Kumar",
      "label": "LAWYER",
      "start_char": 5485,
      "end_char": 5496
    },
    {
      "text": "Tarun Sehgal",
      "label": "OTHER_PERSON",
      "start_char": 5683,
      "end_char": 5695
    },
    {
      "text": "Amit Bansal",
      "label": "PETITIONER",
      "start_char": 5707,
      "end_char": 5718
    },
    {
      "text": "Article 227",
      "label": "PROVISION",
      "start_char": 5850,
      "end_char": 5861
    },
    {
      "text": "Constitution of India",
      "label": "STATUTE",
      "start_char": 5869,
      "end_char": 5890
    },
    {
      "text": "Amit Bansal",
      "label": "PETITIONER",
      "start_char": 6104,
      "end_char": 6115
    },
    {
      "text": "Tarun Sehgal",
      "label": "OTHER_PERSON",
      "start_char": 6128,
      "end_char": 6140
    },
    {
      "text": "30th September 2015",
      "label": "DATE",
      "start_char": 6482,
      "end_char": 6501
    },
    {
      "text": "24 th August 2015",
      "label": "DATE",
      "start_char": 6582,
      "end_char": 6599
    },
    {
      "text": "SRS Real Infrastructure Limited",
      "label": "ORG",
      "start_char": 6634,
      "end_char": 6665
    },
    {
      "text": "SRS",
      "label": "ORG",
      "start_char": 6815,
      "end_char": 6818
    },
    {
      "text": "RPP",
      "label": "ORG",
      "start_char": 6820,
      "end_char": 6823
    },
    {
      "text": "SRS",
      "label": "ORG",
      "start_char": 6895,
      "end_char": 6898
    },
    {
      "text": "SRS",
      "label": "ORG",
      "start_char": 6964,
      "end_char": 6967
    },
    {
      "text": "RPP",
      "label": "ORG",
      "start_char": 6971,
      "end_char": 6974
    },
    {
      "text": "19th November 2015",
      "label": "DATE",
      "start_char": 7220,
      "end_char": 7238
    },
    {
      "text": "RPP",
      "label": "ORG",
      "start_char": 7590,
      "end_char": 7593
    },
    {
      "text": "Order XXXVII",
      "label": "PROVISION",
      "start_char": 7600,
      "end_char": 7612
    },
    {
      "text": "CPC",
      "label": "STATUTE",
      "start_char": 7620,
      "end_char": 7623
    },
    {
      "text": "Amit Bansal",
      "label": "PETITIONER",
      "start_char": 7692,
      "end_char": 7703
    },
    {
      "text": "Amit Bansal",
      "label": "PETITIONER",
      "start_char": 7839,
      "end_char": 7850
    },
    {
      "text": "Raj Power Projects",
      "label": "ORG",
      "start_char": 8008,
      "end_char": 8026
    },
    {
      "text": "Tarun Sehgal",
      "label": "OTHER_PERSON",
      "start_char": 8055,
      "end_char": 8067
    },
    {
      "text": "Himoinsa Pvt",
      "label": "ORG",
      "start_char": 8410,
      "end_char": 8422
    },
    {
      "text": "PLAINTIFF",
      "label": "PETITIONER",
      "start_char": 8553,
      "end_char": 8562
    },
    {
      "text": "Raj Power Projects",
      "label": "RESPONDENT",
      "start_char": 8570,
      "end_char": 8588
    },
    {
      "text": "Tarun Sehgal",
      "label": "OTHER_PERSON",
      "start_char": 8952,
      "end_char": 8964
    },
    {
      "text": "CS(Comm) 47/2020",
      "label": "CASE_NUMBER",
      "start_char": 9048,
      "end_char": 9064
    },
    {
      "text": "CSH POWER HIMOINSA PRIVATE LIMITED",
      "label": "ORG",
      "start_char": 9116,
      "end_char": 9150
    },
    {
      "text": "New Delhi",
      "label": "GPE",
      "start_char": 9252,
      "end_char": 9261
    },
    {
      "text": "PLAINITFF",
      "label": "PETITIONER",
      "start_char": 9276,
      "end_char": 9285
    },
    {
      "text": "AMIT BANSAL @ AMIT AGARWAL",
      "label": "OTHER_PERSON",
      "start_char": 9293,
      "end_char": 9319
    },
    {
      "text": "Raj Power Projects",
      "label": "ORG",
      "start_char": 9338,
      "end_char": 9356
    },
    {
      "text": "Shakarpur",
      "label": "GPE",
      "start_char": 9420,
      "end_char": 9429
    },
    {
      "text": "New Delhi-",
      "label": "GPE",
      "start_char": 9431,
      "end_char": 9441
    },
    {
      "text": "New Delhi-",
      "label": "GPE",
      "start_char": 9493,
      "end_char": 9503
    },
    {
      "text": "9th March 2021",
      "label": "DATE",
      "start_char": 9546,
      "end_char": 9560
    },
    {
      "text": "09.3.2021",
      "label": "DATE",
      "start_char": 9682,
      "end_char": 9691
    },
    {
      "text": "Manas Tripathi",
      "label": "OTHER_PERSON",
      "start_char": 9707,
      "end_char": 9721
    },
    {
      "text": "Amit Bansal",
      "label": "PETITIONER",
      "start_char": 9895,
      "end_char": 9906
    },
    {
      "text": "Aggarwal",
      "label": "OTHER_PERSON",
      "start_char": 9907,
      "end_char": 9915
    },
    {
      "text": "Raj Power Projects",
      "label": "ORG",
      "start_char": 9951,
      "end_char": 9969
    },
    {
      "text": "Amit Bansal",
      "label": "PETITIONER",
      "start_char": 10025,
      "end_char": 10036
    },
    {
      "text": "03.05.2021",
      "label": "DATE",
      "start_char": 10245,
      "end_char": 10255
    },
    {
      "text": "23rd October 2021",
      "label": "DATE",
      "start_char": 10266,
      "end_char": 10283
    },
    {
      "text": "Tarun Sehgal",
      "label": "OTHER_PERSON",
      "start_char": 10446,
      "end_char": 10458
    },
    {
      "text": "Tarun Sehgal",
      "label": "OTHER_PERSON",
      "start_char": 10675,
      "end_char": 10687
    },
    {
      "text": "Amit Bansal @ Amit Aggarwal",
      "label": "RESPONDENT",
      "start_char": 10779,
      "end_char": 10806
    },
    {
      "text": "09.03.2021",
      "label": "DATE",
      "start_char": 10848,
      "end_char": 10858
    },
    {
      "text": "Amit Bansal",
      "label": "PETITIONER",
      "start_char": 10932,
      "end_char": 10943
    },
    {
      "text": "13th April 2022",
      "label": "DATE",
      "start_char": 11344,
      "end_char": 11359
    },
    {
      "text": "Order VI Rule 17",
      "label": "PROVISION",
      "start_char": 11367,
      "end_char": 11383
    },
    {
      "text": "CPC",
      "label": "STATUTE",
      "start_char": 11391,
      "end_char": 11394
    },
    {
      "text": "Tarun Sehgal",
      "label": "OTHER_PERSON",
      "start_char": 11545,
      "end_char": 11557
    },
    {
      "text": "Amit Bansal",
      "label": "PETITIONER",
      "start_char": 11596,
      "end_char": 11607
    },
    {
      "text": "Order VI Rule 17",
      "label": "PROVISION",
      "start_char": 11665,
      "end_char": 11681
    },
    {
      "text": "CPC",
      "label": "STATUTE",
      "start_char": 11689,
      "end_char": 11692
    },
    {
      "text": "Amit Bansal",
      "label": "PETITIONER",
      "start_char": 11828,
      "end_char": 11839
    },
    {
      "text": "Amit Agganval",
      "label": "OTHER_PERSON",
      "start_char": 11846,
      "end_char": 11859
    },
    {
      "text": "Tarun Sehgal",
      "label": "OTHER_PERSON",
      "start_char": 11876,
      "end_char": 11888
    },
    {
      "text": "29th July 2022",
      "label": "DATE",
      "start_char": 12073,
      "end_char": 12087
    },
    {
      "text": "Amit Bansal",
      "label": "PETITIONER",
      "start_char": 12289,
      "end_char": 12300
    },
    {
      "text": "Amit Bansal",
      "label": "PETITIONER",
      "start_char": 12506,
      "end_char": 12517
    },
    {
      "text": "Tarun Sehgal",
      "label": "OTHER_PERSON",
      "start_char": 12526,
      "end_char": 12538
    },
    {
      "text": "Order VI Rule 17",
      "label": "PROVISION",
      "start_char": 12800,
      "end_char": 12816
    },
    {
      "text": "CPC",
      "label": "STATUTE",
      "start_char": 12824,
      "end_char": 12827
    },
    {
      "text": "29th July 2022",
      "label": "DATE",
      "start_char": 13067,
      "end_char": 13081
    },
    {
      "text": "13.4.2022",
      "label": "DATE",
      "start_char": 13526,
      "end_char": 13535
    },
    {
      "text": "29th July 2022",
      "label": "DATE",
      "start_char": 13656,
      "end_char": 13670
    },
    {
      "text": "Raj Power Projects",
      "label": "ORG",
      "start_char": 13777,
      "end_char": 13795
    },
    {
      "text": "Order 1 Rule (2)",
      "label": "PROVISION",
      "start_char": 14080,
      "end_char": 14096
    },
    {
      "text": "CPC",
      "label": "STATUTE",
      "start_char": 14097,
      "end_char": 14100
    },
    {
      "text": "Tarun Sehgal",
      "label": "OTHER_PERSON",
      "start_char": 15057,
      "end_char": 15069
    },
    {
      "text": "Amit Bansal",
      "label": "PETITIONER",
      "start_char": 15137,
      "end_char": 15148
    },
    {
      "text": "Article 227",
      "label": "PROVISION",
      "start_char": 15281,
      "end_char": 15292
    },
    {
      "text": "Constitution of India",
      "label": "STATUTE",
      "start_char": 15300,
      "end_char": 15321
    },
    {
      "text": "Mohit Kumar",
      "label": "LAWYER",
      "start_char": 15344,
      "end_char": 15355
    },
    {
      "text": "Supreme Court",
      "label": "COURT",
      "start_char": 15520,
      "end_char": 15533
    },
    {
      "text": "Kailash v. Nanhku2",
      "label": "PRECEDENT",
      "start_char": 15537,
      "end_char": 15555
    },
    {
      "text": "Ajendraprasadji N. Pande v. Swami Keshavprakeshdasji N. 3",
      "label": "PRECEDENT",
      "start_char": 15560,
      "end_char": 15617
    },
    {
      "text": "1st December 2021",
      "label": "DATE",
      "start_char": 15673,
      "end_char": 15690
    },
    {
      "text": "01.12.2021",
      "label": "DATE",
      "start_char": 15751,
      "end_char": 15761
    },
    {
      "text": "Meenakshi Gupta",
      "label": "OTHER_PERSON",
      "start_char": 15815,
      "end_char": 15830
    },
    {
      "text": "(2005) 4",
      "label": "PRECEDENT",
      "start_char": 16053,
      "end_char": 16061
    },
    {
      "text": "SCC 480 (2006) 12 SCC 1",
      "label": "CASE_NUMBER",
      "start_char": 16062,
      "end_char": 16085
    },
    {
      "text": "20.1.2022",
      "label": "DATE",
      "start_char": 16744,
      "end_char": 16753
    },
    {
      "text": "Mohit Kumar",
      "label": "LAWYER",
      "start_char": 16777,
      "end_char": 16788
    },
    {
      "text": "1st December 2021",
      "label": "DATE",
      "start_char": 16836,
      "end_char": 16853
    },
    {
      "text": "Mohit Kumar",
      "label": "LAWYER",
      "start_char": 16901,
      "end_char": 16912
    },
    {
      "text": "Order XV A",
      "label": "PROVISION",
      "start_char": 16937,
      "end_char": 16947
    },
    {
      "text": "CPC",
      "label": "STATUTE",
      "start_char": 16955,
      "end_char": 16958
    },
    {
      "text": "Commercial Courts Act, 2015",
      "label": "STATUTE",
      "start_char": 16977,
      "end_char": 17004
    },
    {
      "text": "Clause (d) of Order XV A Rule 2",
      "label": "PROVISION",
      "start_char": 17085,
      "end_char": 17116
    },
    {
      "text": "CPC",
      "label": "STATUTE",
      "start_char": 17124,
      "end_char": 17127
    },
    {
      "text": "Order XIV",
      "label": "PROVISION",
      "start_char": 17434,
      "end_char": 17443
    },
    {
      "text": "Code of Civil Procedure, 1908 (5 of 1908)",
      "label": "STATUTE",
      "start_char": 17451,
      "end_char": 17492
    },
    {
      "text": "rule 2 of Order X",
      "label": "PROVISION",
      "start_char": 17612,
      "end_char": 17629
    },
    {
      "text": "Mohit Kumar",
      "label": "LAWYER",
      "start_char": 18158,
      "end_char": 18169
    },
    {
      "text": "Order VI Rule 17",
      "label": "PROVISION",
      "start_char": 18230,
      "end_char": 18246
    },
    {
      "text": "CPC",
      "label": "STATUTE",
      "start_char": 18254,
      "end_char": 18257
    },
    {
      "text": "Order VI Rule 17",
      "label": "PROVISION",
      "start_char": 18542,
      "end_char": 18558
    },
    {
      "text": "Amit Bansal",
      "label": "PETITIONER",
      "start_char": 18667,
      "end_char": 18678
    },
    {
      "text": "Tarun Sehgal",
      "label": "OTHER_PERSON",
      "start_char": 18687,
      "end_char": 18699
    },
    {
      "text": "Mohit Kumar",
      "label": "LAWYER",
      "start_char": 18705,
      "end_char": 18716
    },
    {
      "text": "Order VI Rule 17",
      "label": "PROVISION",
      "start_char": 18777,
      "end_char": 18793
    },
    {
      "text": "CPC",
      "label": "STATUTE",
      "start_char": 18801,
      "end_char": 18804
    },
    {
      "text": "Mohit Kumar",
      "label": "LAWYER",
      "start_char": 18888,
      "end_char": 18899
    },
    {
      "text": "Tarun Sehgal",
      "label": "OTHER_PERSON",
      "start_char": 19127,
      "end_char": 19139
    },
    {
      "text": "Amit Bansal",
      "label": "PETITIONER",
      "start_char": 19172,
      "end_char": 19183
    },
    {
      "text": "Amit Bansal",
      "label": "PETITIONER",
      "start_char": 19256,
      "end_char": 19267
    },
    {
      "text": "Mohit Kumar",
      "label": "LAWYER",
      "start_char": 19303,
      "end_char": 19314
    },
    {
      "text": "Amit Bansal",
      "label": "PETITIONER",
      "start_char": 19470,
      "end_char": 19481
    },
    {
      "text": "Mohit Kumar",
      "label": "LAWYER",
      "start_char": 19599,
      "end_char": 19610
    },
    {
      "text": "Mohit Kumar",
      "label": "LAWYER",
      "start_char": 19756,
      "end_char": 19767
    },
    {
      "text": "Amit Bansal",
      "label": "PETITIONER",
      "start_char": 19880,
      "end_char": 19891
    },
    {
      "text": "Mohit Kumar",
      "label": "LAWYER",
      "start_char": 20059,
      "end_char": 20070
    },
    {
      "text": "C&S Himoinsa Pvt Ltd v. Raj Power Projects",
      "label": "PRECEDENT",
      "start_char": 20222,
      "end_char": 20264
    },
    {
      "text": "Tarun Sehgal",
      "label": "OTHER_PERSON",
      "start_char": 20611,
      "end_char": 20623
    },
    {
      "text": "CPC",
      "label": "STATUTE",
      "start_char": 20802,
      "end_char": 20805
    },
    {
      "text": "Mohit Kumar",
      "label": "LAWYER",
      "start_char": 20936,
      "end_char": 20947
    },
    {
      "text": "Raj Power Projects",
      "label": "ORG",
      "start_char": 21419,
      "end_char": 21437
    },
    {
      "text": "Tarun Sehgal",
      "label": "OTHER_PERSON",
      "start_char": 21446,
      "end_char": 21458
    },
    {
      "text": "Amit Bansal",
      "label": "PETITIONER",
      "start_char": 21533,
      "end_char": 21544
    },
    {
      "text": "Amit Bansal",
      "label": "PETITIONER",
      "start_char": 21571,
      "end_char": 21582
    },
    {
      "text": "Tarun Sehgal",
      "label": "OTHER_PERSON",
      "start_char": 21690,
      "end_char": 21702
    },
    {
      "text": "Amit Bansal",
      "label": "PETITIONER",
      "start_char": 21704,
      "end_char": 21715
    },
    {
      "text": "RPP",
      "label": "ORG",
      "start_char": 21738,
      "end_char": 21741
    },
    {
      "text": "Tarun Sehgal",
      "label": "OTHER_PERSON",
      "start_char": 22107,
      "end_char": 22119
    },
    {
      "text": "Amit Bansal",
      "label": "PETITIONER",
      "start_char": 22132,
      "end_char": 22143
    },
    {
      "text": "Amit Bansal",
      "label": "PETITIONER",
      "start_char": 22300,
      "end_char": 22311
    },
    {
      "text": "Mohit Kumar",
      "label": "LAWYER",
      "start_char": 22376,
      "end_char": 22387
    },
    {
      "text": "Mohit Kumar",
      "label": "LAWYER",
      "start_char": 22508,
      "end_char": 22519
    },
    {
      "text": "Amit Bansal",
      "label": "PETITIONER",
      "start_char": 22644,
      "end_char": 22655
    },
    {
      "text": "Tarun Sehgal",
      "label": "OTHER_PERSON",
      "start_char": 22674,
      "end_char": 22686
    },
    {
      "text": "Amit Bansal",
      "label": "PETITIONER",
      "start_char": 22852,
      "end_char": 22863
    },
    {
      "text": "Amit Bansal",
      "label": "PETITIONER",
      "start_char": 23183,
      "end_char": 23194
    },
    {
      "text": "Tarun Sehgal",
      "label": "OTHER_PERSON",
      "start_char": 23206,
      "end_char": 23218
    },
    {
      "text": "Amit Bansal",
      "label": "PETITIONER",
      "start_char": 23225,
      "end_char": 23236
    },
    {
      "text": "Mohit Kumar",
      "label": "LAWYER",
      "start_char": 23396,
      "end_char": 23407
    },
    {
      "text": "Order VI Rule 17",
      "label": "PROVISION",
      "start_char": 23960,
      "end_char": 23976
    },
    {
      "text": "CPC",
      "label": "STATUTE",
      "start_char": 23984,
      "end_char": 23987
    },
    {
      "text": "Supreme Court",
      "label": "COURT",
      "start_char": 24010,
      "end_char": 24023
    },
    {
      "text": "1st September 2022",
      "label": "DATE",
      "start_char": 24079,
      "end_char": 24097
    },
    {
      "text": "Supreme Court",
      "label": "COURT",
      "start_char": 24138,
      "end_char": 24151
    },
    {
      "text": "LIC v. Sanjeev Builders Pvt",
      "label": "PRECEDENT",
      "start_char": 24155,
      "end_char": 24182
    },
    {
      "text": "L.J. Leach & Co. Ltd. v. Jardine Skinner & Co.5",
      "label": "PRECEDENT",
      "start_char": 24864,
      "end_char": 24911
    },
    {
      "text": "2022 SCC OnLine SC 1128 AIR 1957 SC 357",
      "label": "PRECEDENT",
      "start_char": 24984,
      "end_char": 25023
    },
    {
      "text": "T.N. Alloy Foundry Co. Ltd. v. T.N. Electricity Board,6",
      "label": "PRECEDENT",
      "start_char": 25447,
      "end_char": 25502
    },
    {
      "text": "L.J. Leach and Co. Ltd. v. Jardine Skinner and Co.5",
      "label": "PRECEDENT",
      "start_char": 25620,
      "end_char": 25671
    },
    {
      "text": "Charan Das v. Amir Khan7",
      "label": "PRECEDENT",
      "start_char": 26627,
      "end_char": 26651
    },
    {
      "text": "(2004) 3 SCC 392 AIR 1921 PC 50",
      "label": "PRECEDENT",
      "start_char": 26716,
      "end_char": 26747
    },
    {
      "text": "Mohummud Zahoor Ali v. Rutta Koe",
      "label": "PRECEDENT",
      "start_char": 27025,
      "end_char": 27057
    },
    {
      "text": "Pirgonda Hongonda Patil v. Kalgonda Shidgonda Patil8",
      "label": "PRECEDENT",
      "start_char": 27336,
      "end_char": 27388
    },
    {
      "text": "Batchelor",
      "label": "JUDGE",
      "start_char": 27742,
      "end_char": 27751
    },
    {
      "text": "Kisandas Rupchand v. Rachappa Vithoba Shilwant",
      "label": "PRECEDENT",
      "start_char": 27772,
      "end_char": 27818
    },
    {
      "text": "1957 SCR 595 ILR (1909) 33 Bom 644",
      "label": "PRECEDENT",
      "start_char": 28730,
      "end_char": 28764
    },
    {
      "text": "Ganga Bai v. Vijay Kumar10",
      "label": "PRECEDENT",
      "start_char": 29288,
      "end_char": 29314
    },
    {
      "text": "Ganesh Trading Co. v. Moji Ram11",
      "label": "PRECEDENT",
      "start_char": 29732,
      "end_char": 29764
    },
    {
      "text": "(1974) 2 SCC 393 (1978) 2 SCC 91 25",
      "label": "PRECEDENT",
      "start_char": 30548,
      "end_char": 30583
    },
    {
      "text": "South Konkan Distilleries v. Prabhakar Gajanan Naik12",
      "label": "PRECEDENT",
      "start_char": 32125,
      "end_char": 32178
    },
    {
      "text": "A.K. Gupta & Sons Ltd. v. Damodar Valley Corporation13",
      "label": "PRECEDENT",
      "start_char": 32607,
      "end_char": 32661
    },
    {
      "text": "(2008) 14 SCC 632 AIR 1967 SC 96 : (1966) 1 SCR 796",
      "label": "PRECEDENT",
      "start_char": 32685,
      "end_char": 32736
    },
    {
      "text": "Weldon v. Neale14",
      "label": "PRECEDENT",
      "start_char": 32853,
      "end_char": 32870
    },
    {
      "text": "G. Nagamma v. Siromanamma15",
      "label": "PRECEDENT",
      "start_char": 33214,
      "end_char": 33241
    },
    {
      "text": "Order VI Rule 17",
      "label": "PROVISION",
      "start_char": 33791,
      "end_char": 33807
    },
    {
      "text": "CPC",
      "label": "STATUTE",
      "start_char": 33815,
      "end_char": 33818
    },
    {
      "text": "Pankaja v. Yellappa",
      "label": "PRECEDENT",
      "start_char": 34276,
      "end_char": 34295
    },
    {
      "text": "Order VI Rule 17",
      "label": "PROVISION",
      "start_char": 34403,
      "end_char": 34419
    },
    {
      "text": "CPC",
      "label": "STATUTE",
      "start_char": 34427,
      "end_char": 34430
    },
    {
      "text": "L.R.] 19 Q.B. 394 (1996",
      "label": "CASE_NUMBER",
      "start_char": 34845,
      "end_char": 34868
    },
    {
      "text": "SCC 25 (2004) 6 SCC 415",
      "label": "PRECEDENT",
      "start_char": 34872,
      "end_char": 34895
    },
    {
      "text": "T.N. Alloy Foundry Co. Ltd. v. T.N. Electricity Board6",
      "label": "PRECEDENT",
      "start_char": 36771,
      "end_char": 36825
    },
    {
      "text": "Ragu Thilak",
      "label": "OTHER_PERSON",
      "start_char": 37239,
      "end_char": 37250
    },
    {
      "text": "Ragu Thilak D. John v. S. Rayappan, (2001) 2 SCC 4 31",
      "label": "PRECEDENT",
      "start_char": 38658,
      "end_char": 38711
    },
    {
      "text": "Ragu Thilak D. John v. S. Rayappan17",
      "label": "PRECEDENT",
      "start_char": 38716,
      "end_char": 38752
    },
    {
      "text": "Vishwambhar v. Laxminarayan (Dead) through Lrs18.",
      "label": "PRECEDENT",
      "start_char": 39096,
      "end_char": 39145
    },
    {
      "text": "Vineet Kumar v. Mangal Sain Wadhera19",
      "label": "PRECEDENT",
      "start_char": 39318,
      "end_char": 39355
    },
    {
      "text": "Order VI Rule 17",
      "label": "PROVISION",
      "start_char": 39580,
      "end_char": 39596
    },
    {
      "text": "CPC",
      "label": "STATUTE",
      "start_char": 39604,
      "end_char": 39607
    },
    {
      "text": "Supreme Court",
      "label": "COURT",
      "start_char": 39636,
      "end_char": 39649
    },
    {
      "text": "B.K. Narayana Pillai v. Parameshwaran Pillai",
      "label": "PRECEDENT",
      "start_char": 39681,
      "end_char": 39725
    },
    {
      "text": "Rajesh Kumar Aggarwal v. K.K. Modi21",
      "label": "PRECEDENT",
      "start_char": 39733,
      "end_char": 39769
    },
    {
      "text": "B.K. Narayana Pillai20",
      "label": "OTHER_PERSON",
      "start_char": 39771,
      "end_char": 39793
    },
    {
      "text": "Order 6 Rule 17",
      "label": "PROVISION",
      "start_char": 39824,
      "end_char": 39839
    },
    {
      "text": "CPC",
      "label": "STATUTE",
      "start_char": 39840,
      "end_char": 39843
    },
    {
      "text": "(2001) 6 SCC 163 (1984)",
      "label": "PRECEDENT",
      "start_char": 40211,
      "end_char": 40234
    },
    {
      "text": "Supreme Court Cases 712 (2006) 4",
      "label": "CASE_NUMBER",
      "start_char": 40272,
      "end_char": 40304
    },
    {
      "text": "SCC 385",
      "label": "PROVISION",
      "start_char": 40305,
      "end_char": 40312
    },
    {
      "text": "A.K. Gupta & Sons Ltd. v. Damodar Valley Corpn.13",
      "label": "PRECEDENT",
      "start_char": 40810,
      "end_char": 40859
    },
    {
      "text": "Weldon v. Neal14",
      "label": "PRECEDENT",
      "start_char": 41051,
      "end_char": 41067
    },
    {
      "text": "Charan Das v. Amir Khan7",
      "label": "PRECEDENT",
      "start_char": 41387,
      "end_char": 41411
    },
    {
      "text": "L.J. Leach and Co .Ltd.",
      "label": "PRECEDENT",
      "start_char": 41416,
      "end_char": 41439
    },
    {
      "text": "Jardine Skinner",
      "label": "RESPONDENT",
      "start_char": 41443,
      "end_char": 41458
    },
    {
      "text": "Cropper v. Smith22",
      "label": "PRECEDENT",
      "start_char": 41674,
      "end_char": 41692
    },
    {
      "text": "Kisandas Rupchand v Rachappa Vithoba Shilwant9",
      "label": "PRECEDENT",
      "start_char": 41914,
      "end_char": 41960
    },
    {
      "text": "Pirgonda Hongonda Patil v. Kalgonda Shidgonda Patil8",
      "label": "PRECEDENT",
      "start_char": 41973,
      "end_char": 42025
    },
    {
      "text": "D. 700 Cooke v. Gill23",
      "label": "PRECEDENT",
      "start_char": 42211,
      "end_char": 42233
    },
    {
      "text": "Robinson v. Unicos Property Corpn",
      "label": "PRECEDENT",
      "start_char": 42550,
      "end_char": 42583
    },
    {
      "text": "Dornan v. J.W. Ellis and Co. Ltd25",
      "label": "PRECEDENT",
      "start_char": 42762,
      "end_char": 42796
    },
    {
      "text": "Ganga Bai v. Vijay Kumar10",
      "label": "PRECEDENT",
      "start_char": 42995,
      "end_char": 43021
    },
    {
      "text": "Ganesh Trading Co. v. Moji Ram11",
      "label": "PRECEDENT",
      "start_char": 43433,
      "end_char": 43465
    },
    {
      "text": "L.R.] 8 C.P. 107 (1962) 2 All ER 24 (1962) 1 All ER 303",
      "label": "CASE_NUMBER",
      "start_char": 43926,
      "end_char": 43981
    },
    {
      "text": "Rajesh Kumar Aggarwal20",
      "label": "OTHER_PERSON",
      "start_char": 44313,
      "end_char": 44336
    },
    {
      "text": "Order 6 Rule 17",
      "label": "PROVISION",
      "start_char": 44652,
      "end_char": 44667
    },
    {
      "text": "Order VI Rule 17",
      "label": "PROVISION",
      "start_char": 47104,
      "end_char": 47120
    },
    {
      "text": "CPC",
      "label": "STATUTE",
      "start_char": 47128,
      "end_char": 47131
    },
    {
      "text": "Supreme Court",
      "label": "COURT",
      "start_char": 51764,
      "end_char": 51777
    },
    {
      "text": "Supreme Court",
      "label": "COURT",
      "start_char": 51981,
      "end_char": 51994
    },
    {
      "text": "Mohit Kumar",
      "label": "LAWYER",
      "start_char": 52315,
      "end_char": 52326
    },
    {
      "text": "Order VI Rule 17",
      "label": "PROVISION",
      "start_char": 52396,
      "end_char": 52412
    },
    {
      "text": "CPC",
      "label": "STATUTE",
      "start_char": 52420,
      "end_char": 52423
    },
    {
      "text": "Kailash2",
      "label": "OTHER_PERSON",
      "start_char": 52475,
      "end_char": 52483
    },
    {
      "text": "Ajendraprasadji N. Pande3",
      "label": "OTHER_PERSON",
      "start_char": 52488,
      "end_char": 52513
    },
    {
      "text": "Kailash2",
      "label": "OTHER_PERSON",
      "start_char": 52801,
      "end_char": 52809
    },
    {
      "text": "Supreme Court",
      "label": "COURT",
      "start_char": 52943,
      "end_char": 52956
    },
    {
      "text": "Supreme Court",
      "label": "COURT",
      "start_char": 53007,
      "end_char": 53020
    },
    {
      "text": "Ajendraprasadji N. Pande3",
      "label": "OTHER_PERSON",
      "start_char": 53022,
      "end_char": 53047
    },
    {
      "text": "Supreme Court",
      "label": "COURT",
      "start_char": 53098,
      "end_char": 53111
    },
    {
      "text": "Kailash2",
      "label": "OTHER_PERSON",
      "start_char": 53164,
      "end_char": 53172
    },
    {
      "text": "Order VI Rule 17",
      "label": "PROVISION",
      "start_char": 53264,
      "end_char": 53280
    },
    {
      "text": "CPC",
      "label": "STATUTE",
      "start_char": 53288,
      "end_char": 53291
    },
    {
      "text": "Mohinder Kumar Mehra v. Roop Rani Mehra26",
      "label": "PRECEDENT",
      "start_char": 53341,
      "end_char": 53382
    },
    {
      "text": "Order 6 Rule 17",
      "label": "PROVISION",
      "start_char": 53398,
      "end_char": 53413
    },
    {
      "text": "Order 18",
      "label": "PROVISION",
      "start_char": 53883,
      "end_char": 53891
    },
    {
      "text": "CPC",
      "label": "STATUTE",
      "start_char": 53892,
      "end_char": 53895
    },
    {
      "text": "Order 14",
      "label": "PROVISION",
      "start_char": 53983,
      "end_char": 53991
    },
    {
      "text": "Rule (2018) 2",
      "label": "PROVISION",
      "start_char": 54112,
      "end_char": 54125
    },
    {
      "text": "SCC 132 1 of Order 14",
      "label": "PROVISION",
      "start_char": 54126,
      "end_char": 54147
    },
    {
      "text": "Order 15",
      "label": "PROVISION",
      "start_char": 54168,
      "end_char": 54176
    },
    {
      "text": "Vidyabai v. Padmalatha27",
      "label": "PRECEDENT",
      "start_char": 54483,
      "end_char": 54507
    },
    {
      "text": "SCC p. 413",
      "label": "CASE_NUMBER",
      "start_char": 54689,
      "end_char": 54699
    },
    {
      "text": "Code of Civil Procedure",
      "label": "STATUTE",
      "start_char": 55059,
      "end_char": 55082
    },
    {
      "text": "17-5-2010",
      "label": "DATE",
      "start_char": 55390,
      "end_char": 55399
    },
    {
      "text": "10-8-2010",
      "label": "DATE",
      "start_char": 55465,
      "end_char": 55474
    },
    {
      "text": "Order VI Rule 16 or 17",
      "label": "PROVISION",
      "start_char": 55587,
      "end_char": 55609
    },
    {
      "text": "17-1-2011",
      "label": "DATE",
      "start_char": 55613,
      "end_char": 55622
    },
    {
      "text": "26-7-2011",
      "label": "DATE",
      "start_char": 55648,
      "end_char": 55657
    },
    {
      "text": "(2009) 2 SCC 409",
      "label": "CASE_NUMBER",
      "start_char": 56093,
      "end_char": 56109
    },
    {
      "text": "29-8- 2011",
      "label": "DATE",
      "start_char": 56294,
      "end_char": 56304
    },
    {
      "text": "18-1-2012",
      "label": "DATE",
      "start_char": 56372,
      "end_char": 56381
    },
    {
      "text": "No. 1001 of 2011",
      "label": "CASE_NUMBER",
      "start_char": 56416,
      "end_char": 56432
    },
    {
      "text": "14-2-2014",
      "label": "DATE",
      "start_char": 56851,
      "end_char": 56860
    },
    {
      "text": "14-2-2014",
      "label": "DATE",
      "start_char": 57140,
      "end_char": 57149
    },
    {
      "text": "26-7-2011",
      "label": "DATE",
      "start_char": 57349,
      "end_char": 57358
    },
    {
      "text": "case IA No. 1001 of 2011",
      "label": "CASE_NUMBER",
      "start_char": 57396,
      "end_char": 57420
    },
    {
      "text": "Order VI Rule 17",
      "label": "PROVISION",
      "start_char": 57427,
      "end_char": 57443
    },
    {
      "text": "CPC",
      "label": "STATUTE",
      "start_char": 57444,
      "end_char": 57447
    },
    {
      "text": "22-5- 2014",
      "label": "DATE",
      "start_char": 58076,
      "end_char": 58086
    },
    {
      "text": "proviso to Order 6 Rule 17",
      "label": "PROVISION",
      "start_char": 58106,
      "end_char": 58132
    },
    {
      "text": "CPC",
      "label": "STATUTE",
      "start_char": 58133,
      "end_char": 58136
    },
    {
      "text": "14-2- 2014",
      "label": "DATE",
      "start_char": 58489,
      "end_char": 58499
    },
    {
      "text": "Mohinder Kumar Mehra26",
      "label": "OTHER_PERSON",
      "start_char": 59014,
      "end_char": 59036
    },
    {
      "text": "Supreme Court",
      "label": "COURT",
      "start_char": 59057,
      "end_char": 59070
    },
    {
      "text": "Vidyabai27",
      "label": "OTHER_PERSON",
      "start_char": 59132,
      "end_char": 59142
    },
    {
      "text": "Supreme Court",
      "label": "COURT",
      "start_char": 59292,
      "end_char": 59305
    },
    {
      "text": "Supreme Court",
      "label": "COURT",
      "start_char": 59376,
      "end_char": 59389
    },
    {
      "text": "Order VI Rule 17",
      "label": "PROVISION",
      "start_char": 59486,
      "end_char": 59502
    },
    {
      "text": "CPC",
      "label": "STATUTE",
      "start_char": 59510,
      "end_char": 59513
    },
    {
      "text": "Vidyabai27",
      "label": "OTHER_PERSON",
      "start_char": 59572,
      "end_char": 59582
    },
    {
      "text": "Supreme Court",
      "label": "COURT",
      "start_char": 59620,
      "end_char": 59633
    },
    {
      "text": "Vidyabai27",
      "label": "OTHER_PERSON",
      "start_char": 59829,
      "end_char": 59839
    },
    {
      "text": "Mohinder Kumar Mehra26",
      "label": "OTHER_PERSON",
      "start_char": 59844,
      "end_char": 59866
    },
    {
      "text": "Vidyabai27",
      "label": "OTHER_PERSON",
      "start_char": 59937,
      "end_char": 59947
    },
    {
      "text": "Mohinder Kumar Mehra26",
      "label": "OTHER_PERSON",
      "start_char": 60036,
      "end_char": 60058
    },
    {
      "text": "Mohinder Kumar Mehra26",
      "label": "OTHER_PERSON",
      "start_char": 60219,
      "end_char": 60241
    },
    {
      "text": "Supreme Court",
      "label": "COURT",
      "start_char": 60247,
      "end_char": 60260
    },
    {
      "text": "Order VI Rule 17",
      "label": "PROVISION",
      "start_char": 60394,
      "end_char": 60410
    },
    {
      "text": "CPC",
      "label": "STATUTE",
      "start_char": 60418,
      "end_char": 60421
    },
    {
      "text": "Order VI Rule 17",
      "label": "PROVISION",
      "start_char": 60469,
      "end_char": 60485
    },
    {
      "text": "Mohinder Kumar Mehra26",
      "label": "OTHER_PERSON",
      "start_char": 60500,
      "end_char": 60522
    },
    {
      "text": "Mohinder Kumar Mehra26",
      "label": "OTHER_PERSON",
      "start_char": 60906,
      "end_char": 60928
    },
    {
      "text": "Order VI Rule 17",
      "label": "PROVISION",
      "start_char": 61030,
      "end_char": 61046
    },
    {
      "text": "CPC",
      "label": "STATUTE",
      "start_char": 61054,
      "end_char": 61057
    },
    {
      "text": "Mohit Kumar",
      "label": "LAWYER",
      "start_char": 61293,
      "end_char": 61304
    },
    {
      "text": "Supreme Court",
      "label": "COURT",
      "start_char": 61411,
      "end_char": 61424
    },
    {
      "text": "Kailash",
      "label": "OTHER_PERSON",
      "start_char": 61437,
      "end_char": 61444
    },
    {
      "text": "Ajendraprasadji N. Pande3",
      "label": "OTHER_PERSON",
      "start_char": 61463,
      "end_char": 61488
    },
    {
      "text": "Commercial Courts Act, 2015",
      "label": "STATUTE",
      "start_char": 61736,
      "end_char": 61763
    },
    {
      "text": "1st December 2021",
      "label": "DATE",
      "start_char": 61781,
      "end_char": 61798
    },
    {
      "text": "20 th January 2022",
      "label": "DATE",
      "start_char": 61892,
      "end_char": 61910
    },
    {
      "text": "Mohit Kumar",
      "label": "LAWYER",
      "start_char": 61968,
      "end_char": 61979
    },
    {
      "text": "Order XV(A)",
      "label": "PROVISION",
      "start_char": 62011,
      "end_char": 62022
    },
    {
      "text": "CPC",
      "label": "STATUTE",
      "start_char": 62030,
      "end_char": 62033
    },
    {
      "text": "Commercial Courts Act",
      "label": "STATUTE",
      "start_char": 62052,
      "end_char": 62073
    },
    {
      "text": "Order XV(A) Rule 2",
      "label": "PROVISION",
      "start_char": 62075,
      "end_char": 62093
    },
    {
      "text": "CPC",
      "label": "STATUTE",
      "start_char": 62101,
      "end_char": 62104
    },
    {
      "text": "Mohit Kumar",
      "label": "LAWYER",
      "start_char": 62402,
      "end_char": 62413
    },
    {
      "text": "Order XV(A) Rule 2(D)",
      "label": "PROVISION",
      "start_char": 62582,
      "end_char": 62603
    },
    {
      "text": "CPC",
      "label": "STATUTE",
      "start_char": 62611,
      "end_char": 62614
    },
    {
      "text": "Commercial Courts Act",
      "label": "STATUTE",
      "start_char": 62633,
      "end_char": 62654
    },
    {
      "text": "Mohit Kumar",
      "label": "LAWYER",
      "start_char": 62733,
      "end_char": 62744
    },
    {
      "text": "Order VI Rule 17",
      "label": "PROVISION",
      "start_char": 62863,
      "end_char": 62879
    },
    {
      "text": "CPC",
      "label": "STATUTE",
      "start_char": 62887,
      "end_char": 62890
    },
    {
      "text": "Mohit Kumar",
      "label": "LAWYER",
      "start_char": 62994,
      "end_char": 63005
    },
    {
      "text": "Order VI Rule 17",
      "label": "PROVISION",
      "start_char": 63066,
      "end_char": 63082
    },
    {
      "text": "CPC",
      "label": "STATUTE",
      "start_char": 63090,
      "end_char": 63093
    },
    {
      "text": "Amit Bansal",
      "label": "PETITIONER",
      "start_char": 63307,
      "end_char": 63318
    },
    {
      "text": "Tarun Sehgal",
      "label": "OTHER_PERSON",
      "start_char": 63331,
      "end_char": 63343
    },
    {
      "text": "Amit Bansal",
      "label": "PETITIONER",
      "start_char": 63628,
      "end_char": 63639
    },
    {
      "text": "Tarun Sehgal",
      "label": "OTHER_PERSON",
      "start_char": 63649,
      "end_char": 63661
    },
    {
      "text": "Order VI Rule 17",
      "label": "PROVISION",
      "start_char": 63943,
      "end_char": 63959
    },
    {
      "text": "CPC",
      "label": "STATUTE",
      "start_char": 63967,
      "end_char": 63970
    },
    {
      "text": "Order VI Rule 17",
      "label": "PROVISION",
      "start_char": 64022,
      "end_char": 64038
    },
    {
      "text": "CPC",
      "label": "STATUTE",
      "start_char": 64046,
      "end_char": 64049
    },
    {
      "text": "Supreme Court",
      "label": "COURT",
      "start_char": 64071,
      "end_char": 64084
    },
    {
      "text": "Article 227",
      "label": "PROVISION",
      "start_char": 64326,
      "end_char": 64337
    },
    {
      "text": "Constitution of India",
      "label": "STATUTE",
      "start_char": 64345,
      "end_char": 64366
    },
    {
      "text": "Delhi High Court Legal Services Committee",
      "label": "COURT",
      "start_char": 64797,
      "end_char": 64838
    },
    {
      "text": "C.HARI SHANKAR",
      "label": "JUDGE",
      "start_char": 64985,
      "end_char": 64999
    },
    {
      "text": "SEPTEMBER 14, 2022",
      "label": "DATE",
      "start_char": 65003,
      "end_char": 65021
    }
  ],
  "precedent_clusters": {
    "L.J. Leach & Co. Ltd. v. Jardine Skinner & Co.5": [
      "Sugandhi v. P. Raj Kumar1",
      "Kailash v. Nanhku2",
      "Ajendraprasadji N. Pande v. Swami Keshavprakeshdasji N. 3",
      "(2005) 4",
      "C&S Himoinsa Pvt Ltd v. Raj Power Projects",
      "LIC v. Sanjeev Builders Pvt",
      "L.J. Leach & Co. Ltd. v. Jardine Skinner & Co.5",
      "T.N. Alloy Foundry Co. Ltd. v. T.N. Electricity Board,6",
      "L.J. Leach and Co. Ltd. v. Jardine Skinner and Co.5",
      "Charan Das v. Amir Khan7",
      "Mohummud Zahoor Ali v. Rutta Koe",
      "Pirgonda Hongonda Patil v. Kalgonda Shidgonda Patil8",
      "Kisandas Rupchand v. Rachappa Vithoba Shilwant",
      "Ganga Bai v. Vijay Kumar10",
      "Ganesh Trading Co. v. Moji Ram11",
      "South Konkan Distilleries v. Prabhakar Gajanan Naik12",
      "A.K. Gupta & Sons Ltd. v. Damodar Valley Corporation13",
      "Weldon v. Neale14",
      "G. Nagamma v. Siromanamma15",
      "Pankaja v. Yellappa",
      "T.N. Alloy Foundry Co. Ltd. v. T.N. Electricity Board6",
      "Ragu Thilak D. John v. S. Rayappan17",
      "Vineet Kumar v. Mangal Sain Wadhera19",
      "B.K. Narayana Pillai v. Parameshwaran Pillai",
      "Rajesh Kumar Aggarwal v. K.K. Modi21",
      "A.K. Gupta & Sons Ltd. v. Damodar Valley Corpn.13",
      "Weldon v. Neal14",
      "Charan Das v. Amir Khan7",
      "L.J. Leach and Co .Ltd.",
      "Cropper v. Smith22",
      "Kisandas Rupchand v Rachappa Vithoba Shilwant9",
      "Pirgonda Hongonda Patil v. Kalgonda Shidgonda Patil8",
      "Robinson v. Unicos Property Corpn",
      "Dornan v. J.W. Ellis and Co. Ltd25",
      "Ganga Bai v. Vijay Kumar10",
      "Ganesh Trading Co. v. Moji Ram11",
      "Mohinder Kumar Mehra v. Roop Rani Mehra26",
      "Vidyabai v. Padmalatha27"
    ]
  },
  "statute_clusters": {},
  "provision_statute_pairs": [
    [
      "Article 227",
      "Constitution of India",
      "Article 227",
      "Constitution of India"
    ],
    [
      "Order VI Rule 17",
      "CPC",
      "Order VI Rule 17",
      "CPC"
    ],
    [
      "Article 227",
      "Constitution of India",
      "Article 227",
      "Constitution of India"
    ],
    [
      "Article 227",
      "Constitution of India",
      "Article 227",
      "Constitution of India"
    ],
    [
      "Order XXXVII",
      "CPC",
      "Order XXXVII",
      "CPC"
    ],
    [
      "Order VI Rule 17",
      "CPC",
      "Order VI Rule 17",
      "CPC"
    ],
    [
      "Order VI Rule 17",
      "CPC",
      "Order VI Rule 17",
      "CPC"
    ],
    [
      "Order VI Rule 17",
      "CPC",
      "Order VI Rule 17",
      "CPC"
    ],
    [
      "Order 1 Rule (2)",
      "CPC",
      "Order 1 Rule (2)",
      "CPC"
    ],
    [
      "Article 227",
      "Constitution of India",
      "Article 227",
      "Constitution of India"
    ],
    [
      "Order XV A",
      "CPC",
      "Order XV A",
      "CPC"
    ],
    [
      "Clause (d) of Order XV A Rule 2",
      "CPC",
      "Clause (d) of Order XV A Rule 2",
      "CPC"
    ],
    [
      "Order XIV",
      "Code of Civil Procedure, 1908 (5 of 1908)",
      "Order XIV",
      "Code of Civil Procedure, 1908 (5 of 1908)"
    ],
    [
      "Order VI Rule 17",
      "CPC",
      "Order VI Rule 17",
      "CPC"
    ],
    [
      "Order VI Rule 17",
      "CPC",
      "Order VI Rule 17",
      "CPC"
    ],
    [
      "Order VI Rule 17",
      "CPC",
      "Order VI Rule 17",
      "CPC"
    ],
    [
      "Order VI Rule 17",
      "CPC",
      "Order VI Rule 17",
      "CPC"
    ],
    [
      "Order VI Rule 17",
      "CPC",
      "Order VI Rule 17",
      "CPC"
    ],
    [
      "Order VI Rule 17",
      "CPC",
      "Order VI Rule 17",
      "CPC"
    ],
    [
      "Order 6 Rule 17",
      "CPC",
      "Order 6 Rule 17",
      "CPC"
    ],
    [
      "Order VI Rule 17",
      "CPC",
      "Order VI Rule 17",
      "CPC"
    ],
    [
      "Order VI Rule 17",
      "CPC",
      "Order VI Rule 17",
      "CPC"
    ],
    [
      "Order VI Rule 17",
      "CPC",
      "Order VI Rule 17",
      "CPC"
    ],
    [
      "Order 18",
      "CPC",
      "Order 18",
      "CPC"
    ],
    [
      "Order VI Rule 17",
      "CPC",
      "Order VI Rule 17",
      "CPC"
    ],
    [
      "proviso to Order 6 Rule 17",
      "CPC",
      "proviso to Order 6 Rule 17",
      "CPC"
    ],
    [
      "Order VI Rule 17",
      "CPC",
      "Order VI Rule 17",
      "CPC"
    ],
    [
      "Order VI Rule 17",
      "CPC",
      "Order VI Rule 17",
      "CPC"
    ],
    [
      "Order VI Rule 17",
      "CPC",
      "Order VI Rule 17",
      "CPC"
    ],
    [
      "Order XV(A)",
      "CPC",
      "Order XV(A)",
      "CPC"
    ],
    [
      "Order XV(A) Rule 2",
      "CPC",
      "Order XV(A) Rule 2",
      "CPC"
    ],
    [
      "Order XV(A) Rule 2(D)",
      "CPC",
      "Order XV(A) Rule 2(D)",
      "CPC"
    ],
    [
      "Order VI Rule 17",
      "CPC",
      "Order VI Rule 17",
      "CPC"
    ],
    [
      "Order VI Rule 17",
      "CPC",
      "Order VI Rule 17",
      "CPC"
    ],
    [
      "Order VI Rule 17",
      "CPC",
      "Order VI Rule 17",
      "CPC"
    ],
    [
      "Order VI Rule 17",
      "CPC",
      "Order VI Rule 17",
      "CPC"
    ],
    [
      "Article 227",
      "Constitution of India",
      "Article 227",
      "Constitution of India"
    ],
    [
      "Order VI Rule 17",
      "CPC",
      "Order VI Rule 17",
      "CPC"
    ],
    [
      "Order 6 Rule 17",
      "CPC",
      "Order 6 Rule 17",
      "CPC"
    ],
    [
      "Order 6 Rule 17",
      "CPC",
      "Order 6 Rule 17",
      "CPC"
    ],
    [
      "SCC 132 1 of Order 14",
      "CPC",
      "SCC 132 1 of Order 14",
      "CPC"
    ],
    [
      "Order VI Rule 17",
      "CPC",
      "Order VI Rule 17",
      "CPC"
    ],
    [
      "subrule (3)",
      "Code of Civil Procedure, 1908",
      "subrule (3)",
      "Code of Civil Procedure, 1908"
    ],
    [
      "rule 2 of Order X",
      "Code of Civil Procedure, 1908 (5 of 1908)",
      "rule 2 of Order X",
      "Code of Civil Procedure, 1908 (5 of 1908)"
    ],
    [
      "SCC 385",
      "CPC",
      "SCC 385",
      "CPC"
    ],
    [
      "Order 14",
      "CPC",
      "Order 14",
      "CPC"
    ],
    [
      "Rule (2018) 2",
      "CPC",
      "Rule (2018) 2",
      "CPC"
    ],
    [
      "Order 15",
      "CPC",
      "Order 15",
      "CPC"
    ],
    [
      "Order VI Rule 16 or 17",
      "Code of Civil Procedure",
      "Order VI Rule 16 or 17",
      "Code of Civil Procedure"
    ]
  ],
  "precedent_counts": {
    "L.J. Leach & Co. Ltd. v. Jardine Skinner & Co.5": 38
  },
  "provision_counts": {
    "Article 227 of Constitution of India": 5,
    "Order VI Rule 17 of CPC": 23,
    "Order XXXVII of CPC": 1,
    "Order 1 Rule (2) of CPC": 1,
    "Order XV A of CPC": 1,
    "Clause (d) of Order XV A Rule 2 of CPC": 1,
    "Order XIV of Code of Civil Procedure, 1908 (5 of 1908)": 1,
    "Order 6 Rule 17 of CPC": 3,
    "Order 18 of CPC": 1,
    "proviso to Order 6 Rule 17 of CPC": 1,
    "Order XV(A) of CPC": 1,
    "Order XV(A) Rule 2 of CPC": 1,
    "Order XV(A) Rule 2(D) of CPC": 1,
    "SCC 132 1 of Order 14 of CPC": 1,
    "subrule (3) of Code of Civil Procedure, 1908": 1,
    "rule 2 of Order X of Code of Civil Procedure, 1908 (5 of 1908)": 1,
    "SCC 385 of CPC": 1,
    "Order 14 of CPC": 1,
    "Rule (2018) 2 of CPC": 1,
    "Order 15 of CPC": 1,
    "Order VI Rule 16 or 17 of Code of Civil Procedure": 1
  },
  "statute_counts": {
    "Constitution of India": 5,
    "CPC": 40,
    "Code of Civil Procedure, 1908 (5 of 1908)": 2,
    "Code of Civil Procedure, 1908": 1,
    "Code of Civil Procedure": 1
  }
}